bluepyemodel/__init__.py
bluepyemodel/access_point/__init__.py
bluepyemodel/access_point/access_point.py
bluepyemodel/access_point/forge_access_point.py
bluepyemodel/access_point/local.py
bluepyemodel/access_point/nexus.py
bluepyemodel/data/ISI_CV_Shai2015.csv
bluepyemodel/data/__init__.py
bluepyemodel/data/spike_rheobase_pA_BeaulieuLaroche2021.csv
bluepyemodel/data/utils.py
bluepyemodel/ecode/__init__.py
bluepyemodel/ecode/apwaveform.py
bluepyemodel/ecode/comb.py
bluepyemodel/ecode/customfromfile.py
bluepyemodel/ecode/dehyperpol.py
bluepyemodel/ecode/dendrite.py
bluepyemodel/ecode/firepattern.py
bluepyemodel/ecode/hyperdepol.py
bluepyemodel/ecode/idrest.py
bluepyemodel/ecode/iv.py
bluepyemodel/ecode/negcheops.py
bluepyemodel/ecode/noise.py
bluepyemodel/ecode/noiseou3.py
bluepyemodel/ecode/poscheops.py
bluepyemodel/ecode/probampanmda_ems.py
bluepyemodel/ecode/ramp.py
bluepyemodel/ecode/random_square_inputs.py
bluepyemodel/ecode/sahp.py
bluepyemodel/ecode/sinespec.py
bluepyemodel/ecode/spikerec.py
bluepyemodel/ecode/square.py
bluepyemodel/ecode/stimulus.py
bluepyemodel/ecode/subwhitenoise.py
bluepyemodel/ecode/thresholdaddition.py
bluepyemodel/ecode/whitenoise.py
bluepyemodel/ecode/data/NoiseOU3.txt
bluepyemodel/ecode/data/SubWhiteNoise.txt
bluepyemodel/ecode/data/WhiteNoise.txt
bluepyemodel/efeatures_extraction/__init__.py
bluepyemodel/efeatures_extraction/auto_targets.py
bluepyemodel/efeatures_extraction/efeatures_extraction.py
bluepyemodel/efeatures_extraction/target.py
bluepyemodel/efeatures_extraction/targets_configuration.py
bluepyemodel/efeatures_extraction/targets_configurator.py
bluepyemodel/efeatures_extraction/trace_file.py
bluepyemodel/emodel_pipeline/__init__.py
bluepyemodel/emodel_pipeline/emodel.py
bluepyemodel/emodel_pipeline/emodel_metadata.py
bluepyemodel/emodel_pipeline/emodel_pipeline.py
bluepyemodel/emodel_pipeline/emodel_script.py
bluepyemodel/emodel_pipeline/emodel_settings.py
bluepyemodel/emodel_pipeline/emodel_workflow.py
bluepyemodel-1.0.38.dist-info/licenses/AUTHORS.txt
bluepyemodel-1.0.38.dist-info/licenses/COPYING
bluepyemodel-1.0.38.dist-info/licenses/LICENSE.txt
bluepyemodel-1.0.38.dist-info/METADATA
bluepyemodel-1.0.38.dist-info/WHEEL
bluepyemodel-1.0.38.dist-info/top_level.txt
bluepyemodel-1.0.38.dist-info/RECORD
