Metadata-Version: 2.4
Name: bluepyemodel
Version: 1.0.38
Summary: Blue Brain Python Electrical Modeling Pipeline
Author: Blue Brain Project, EPFL
License: BluePyEModel is licensed under the Apache License, unless noted otherwise, e.g., for external
Project-URL: Homepage, https://github.com/openbraininstitute/BluePyEModel
Keywords: computational neuroscience,simulation,analysis,parameters,Blue Brain Project
Classifier: Development Status :: 5 - Production/Stable
Classifier: Environment :: Console
Classifier: License :: OSI Approved :: Apache Software License
Classifier: Operating System :: POSIX
Classifier: Topic :: Scientific/Engineering
Classifier: Programming Language :: Python :: 3
Classifier: Topic :: Utilities
Requires-Python: >=3.11
License-File: LICENSE.txt
License-File: COPYING
License-File: AUTHORS.txt
Requires-Dist: numpy
Requires-Dist: scipy>=1.16.1
Requires-Dist: pandas
Requires-Dist: ipyparallel>=6.3
Requires-Dist: tqdm
Requires-Dist: pyyaml
Requires-Dist: gitpython
Requires-Dist: bluepyopt>=1.14.10
Requires-Dist: bluepyefe>=2.3.48
Requires-Dist: neurom>=3.0
Requires-Dist: efel>=5.5.5
Requires-Dist: configparser
Requires-Dist: neuron>=8.0
Requires-Dist: morph_tool>=2.8
Requires-Dist: morphio
Requires-Dist: fasteners>=0.16
Requires-Dist: jinja2>=3.0.3
Requires-Dist: currentscape>=0.0.11
Provides-Extra: luigi
Requires-Dist: luigi>=3.0; extra == "luigi"
Requires-Dist: luigi-tools>=0.0.12; extra == "luigi"
Provides-Extra: docs
Requires-Dist: graphviz; extra == "docs"
Requires-Dist: sphinx<9; extra == "docs"
Requires-Dist: sphinx-bluebrain-theme; extra == "docs"
Requires-Dist: luigi>=3.0; extra == "docs"
Requires-Dist: luigi-tools>=0.0.12; extra == "docs"
Provides-Extra: test
Requires-Dist: pytest>=6.2; extra == "test"
Requires-Dist: dictdiffer>=0.8; extra == "test"
Provides-Extra: nexus
Requires-Dist: nexusforge>=0.8.2; extra == "nexus"
Requires-Dist: entity_management>=1.2; extra == "nexus"
Requires-Dist: pyJWT>=2.1.0; extra == "nexus"
Provides-Extra: all
Requires-Dist: luigi>=3.0; extra == "all"
Requires-Dist: luigi-tools>=0.0.12; extra == "all"
Requires-Dist: nexusforge>=0.8.2; extra == "all"
Requires-Dist: entity_management>=1.2; extra == "all"
Requires-Dist: pyJWT>=2.1.0; extra == "all"
Requires-Dist: pytest>=6.2; extra == "all"
Requires-Dist: dictdiffer>=0.8; extra == "all"
Dynamic: license-file
